scrapy_translate/__init__.py
scrapy_translate/pipeline.py
scrapy_translate/processors.py
scrapy_translate/providers.py
scrapy_translate-1.3.dist-info/licenses/LICENSE
scrapy_translate-1.3.dist-info/METADATA
scrapy_translate-1.3.dist-info/WHEEL
scrapy_translate-1.3.dist-info/top_level.txt
scrapy_translate-1.3.dist-info/RECORD
