Metadata-Version: 2.4
Name: scrapy-translate
Version: 1.3
Summary: Scrapy text translation pipeline
Author-email: Ivan Frolov <ivofrolov@fastmail.com>
License-Expression: MIT
Project-URL: Homepage, https://github.com/ivofrolov/scrapy-translate
Project-URL: Issues, https://github.com/ivofrolov/scrapy-translate/issues
Classifier: Framework :: Scrapy
Classifier: Development Status :: 5 - Production/Stable
Classifier: Environment :: Console
Classifier: Intended Audience :: Developers
Classifier: Operating System :: OS Independent
Classifier: Programming Language :: Python
Classifier: Programming Language :: Python :: 3
Classifier: Programming Language :: Python :: 3.9
Classifier: Programming Language :: Python :: 3.10
Classifier: Programming Language :: Python :: 3.11
Classifier: Programming Language :: Python :: 3.12
Classifier: Programming Language :: Python :: 3.13
Classifier: Programming Language :: Python :: 3.14
Requires-Python: >=3.9
License-File: LICENSE
Requires-Dist: scrapy~=2.12
Dynamic: license-file
